igapi/__init__.py
ig_trading_api-1.0.6.dist-info/LICENSE
ig_trading_api-1.0.6.dist-info/METADATA
ig_trading_api-1.0.6.dist-info/WHEEL
ig_trading_api-1.0.6.dist-info/top_level.txt
ig_trading_api-1.0.6.dist-info/RECORD
