Metadata-Version: 2.1
Name: ig-trading-api
Version: 1.0.6
Summary: Simple IG trading API for Python
Home-page: https://github.com/Iceloof/IG-API
Author: Hurin Hu
Author-email: hurin@live.ca
Classifier: Programming Language :: Python :: 3
Classifier: License :: OSI Approved :: MIT License
Classifier: Operating System :: OS Independent
Requires-Python: >=3.6
License-File: LICENSE
Requires-Dist: pytz
Requires-Dist: pandas
Requires-Dist: pycryptodome
